petaly/__init__.py
petaly/__main__.py
petaly/cli/__init__.py
petaly/cli/cli.py
petaly/cli/cli_cleanup.py
petaly/cli/cli_initializer.py
petaly/cli/cli_menu.py
petaly/cli/cli_visualizer.py
petaly/connectors/__init__.py
petaly/connectors/bigquery/__init__.py
petaly/connectors/bigquery/bq_connector.py
petaly/connectors/bigquery/bq_extractor.py
petaly/connectors/bigquery/bq_loader.py
petaly/connectors/bigquery/metadata.sql
petaly/connectors/bigquery/config/connector_attributes.json
petaly/connectors/bigquery/config/create_table_stmt.sql
petaly/connectors/bigquery/config/extract_to_stmt.sql
petaly/connectors/bigquery/config/extractor_type_transformer.json
petaly/connectors/bigquery/config/load_from_stmt.json
petaly/connectors/bigquery/type_mapping/bigquery.json
petaly/connectors/bigquery/type_mapping/csv.json
petaly/connectors/bigquery/type_mapping/mysql.json
petaly/connectors/bigquery/type_mapping/postgres.json
petaly/connectors/bigquery/type_mapping/redshift.json
petaly/connectors/csv/__init__.py
petaly/connectors/csv/csv_connector.py
petaly/connectors/csv/csv_extractor.py
petaly/connectors/csv/csv_loader.py
petaly/connectors/csv/config/connector_attributes.json
petaly/connectors/csv/config/extractor_type_transformer.json
petaly/connectors/csv/type_mapping/bigquery.json
petaly/connectors/csv/type_mapping/csv.json
petaly/connectors/csv/type_mapping/mysql.json
petaly/connectors/csv/type_mapping/postgres.json
petaly/connectors/csv/type_mapping/redshift.json
petaly/connectors/gs/__init__.py
petaly/connectors/gs/gs_connector.py
petaly/connectors/gs/gs_extractor.py
petaly/connectors/gs/gs_loader.py
petaly/connectors/gs/config/connector_attributes.json
petaly/connectors/gs/config/extractor_type_transformer.json
petaly/connectors/mysql/__init__.py
petaly/connectors/mysql/metadata.sql
petaly/connectors/mysql/mysql_connector.py
petaly/connectors/mysql/mysql_extractor.py
petaly/connectors/mysql/mysql_loader.py
petaly/connectors/mysql/config/connector_attributes.json
petaly-0.1.0.dist-info/licenses/LICENSE.md
petaly-0.1.0.dist-info/METADATA
petaly-0.1.0.dist-info/WHEEL
petaly-0.1.0.dist-info/entry_points.txt
petaly-0.1.0.dist-info/top_level.txt
petaly-0.1.0.dist-info/RECORD
