Metadata-Version: 2.4
Name: petaly
Version: 0.1.0
Summary: Python ETL and Data Pipeline Tool
Author-email: Pavel Rabaev <contact@petaly.org>
Maintainer-email: Pavel Rabaev <contact@petaly.org>
License-Expression: Apache-2.0
Project-URL: Homepage, https://petaly.org
Keywords: petaly,etl,ingestion,database,postgres,postgresql,mysql,bigquery,redshift,s3,gcs,google storage,bucket
Classifier: Development Status :: 4 - Beta
Classifier: Intended Audience :: Developers
Classifier: Topic :: Database :: Database Engines/Servers
Classifier: Programming Language :: Python :: 3
Classifier: Programming Language :: Python :: 3.10
Classifier: Programming Language :: Python :: 3.11
Classifier: Programming Language :: Python :: 3.12
Classifier: Programming Language :: Python :: 3.13
Requires-Python: >=3.10
License-File: LICENSE.md
Requires-Dist: PyYAML
Requires-Dist: PyMySQL
Requires-Dist: cryptography
Requires-Dist: pyarrow
Requires-Dist: rich
Requires-Dist: psycopg
Requires-Dist: psycopg-binary
Requires-Dist: mysql-connector-python
Requires-Dist: jsonschema
Provides-Extra: gcp
Requires-Dist: google-cloud; extra == "gcp"
Requires-Dist: google-cloud-bigquery; extra == "gcp"
Requires-Dist: google-cloud-storage; extra == "gcp"
Requires-Dist: google-api-python-client; extra == "gcp"
Requires-Dist: oauth2client; extra == "gcp"
Provides-Extra: aws
Requires-Dist: redshift_connector[full]; extra == "aws"
Provides-Extra: all
Requires-Dist: petaly[gcp]; extra == "all"
Requires-Dist: petaly[aws]; extra == "all"
Dynamic: license-file
